{
    "UNKNOWN": "Erro de serviço",
    "INVALID_ETH_ADDRESS": "Endereço Ethereum inválido, verifique novamente.",
    "Retry": "Tentar novamente",
    "INVALID_L2_TX": "Falha no(s) depósito(s)",
    "INVALID_CLIENT_TRANSFER_ID": "ID de transferência do cliente inválida. A ID de transferência do cliente é {{clientTransferId}}.",
    "INVALID_PAGE_SIZE": "Tamanho inválido. O tamanho é {{size}}.",
    "EMPTY_PARAM": "{{name}} está vazio.",
    "EMPTY_CLIENT_WITHDRAW_ID": "ID de saque do cliente vazia.",
    "EMPTY_CLIENT_TRANSFER_ID": "Parâmetro vazio de ID de transferência do cliente. Preencha-o.",
    "AMOUNT_MUST_GREETER_ZERO": "O valor deve ser maior que 0. O valor é {{amount}}.",
    "ACCOUNT_NOT_FOUND": "Conta não encontrada. A ID da conta é {{accountId}}.",
    "ACCOUNT_NOT_FOUND_L2KEY": "Conta não encontrada para esta chave L2.",
    "ORDER_NOT_CANCEL_MATCHED": "O pedido está no processamento, não cancele.",
    "ORDER_NOT_CANCEL_FILLED": "Pedido bem-sucedido, não cancele.",
    "ORDER_NOT_CANCEL_INVALID_STATUS": "Pedido inválido, não cancele.",
    "ORDER_INVALID_ORDER_TYPE": "Tipo de ordem inválido. O tipo de ordem é {{orderType}}.",
    "AccountLeverage": "Alavancagem de conta",
    "action": "Ação",
    "active": "Ativo",
    "adl": "ADL",
    "all": "TUDO",
    "ALL": "Tudo",
    "allActiveOrders": "Todas as ordens ativas",
    "allConditionalOrders": "Todas as ordens condicionais",
    "allMarkets": "Todos os mercados",
    "Amount": "Valor",
    "amount": "Valor",
    "amountEmptyWarn": "O valor do depósito não pode ser vazio.",
    "amountRequired": "O valor do saque não pode ser vazio.",
    "announcement": "Anúncios",
    "apexPro": "ApeX Pro",
    "apexProDesc": "Trading de contrato perpétuo no ApeX Pro com base no livro de ordens",
    "approveErrorWithMessage": "Erro de aprovação",
    "approveSuccess": "Aprovação bem-sucedida",
    "Asset": "Ativo",
    "assets": "Ativos",
    "Available": "Disponível",
    "availableBalance": "Saldo disponível",
    "Balance": "Saldo",
    "balance": "Saldo",
    "btnAdd": "+Adicionar",
    "btnCancel": "Cancelar",
    "btnCancelAll": "Cancelar tudo",
    "btnConfirm": "Confirmar",
    "BUY": "Comprar",
    "buySuccessByLimitInfo": "{{qty}} contrato(s) {{token}} serão comprados pelo preço de {{price}}.",
    "buySuccessByMarketInfo": "{{qty}} contrato(s) {{token}} serão comprados pelo preço de mercado.",
    "CANCELED": "Cancelado",
    "CANCELING": "Cancelando",
    "Chain": "Cadeia",
    "chainAvailable": "Cadeia disponível",
    "chainMax": "Cadeia disponível",
    "changeWallet": "Alterar carteira",
    "charts": "Tabelas",
    "choose.goerli.network": "Antes, alterne para Goerli Testnet.",
    "closeBy": "Fechamento por",
    "closeByLimit": "Fechamento por limite",
    "closedPnL": "P&L fechado",
    "closeLong": "Fechar Long",
    "closePnL": "P&L fechado",
    "closePrice": "Preço de fechamento",
    "closeQty": "Quantidade de fechamento",
    "closeShort": "Fechar Short",
    "coin": "Moeda",
    "community": "Comunidade",
    "condition": "Condição",
    "conditional": "Condicional",
    "CONDITIONAL_LIMIT": "Limite condicional",
    "CONDITIONAL_MARKET": "Mercado condicional",
    "conditionalLimit": "Limite condicional",
    "conditionalMarket": "Mercado condicional",
    "confirmDeposit": "Confirmar depósito",
    "Confirmed": "Confirmado",
    "Confirmed_Withdrawing": "Pronto",
    "confirmOwner": "Confirme que você é o proprietário da carteira.",
    "confirmWithdraw": "Confirmar saque",
    "confirmWithdrawDesc2": "Depois de iniciados, os saques são irreversíveis.",
    "connectEthermWallet": "Conecte sua carteira Ethereum para depositar fundos e começar a fazer trading.",
    "connectWallet": "Conectar carteira",
    "connectWalletFirst": "Primeiro, conecte a carteira",
    "connectWalletTips": "Conectar minha carteira e definir a rede da carteira como 'Goerli Testnet'.",
    "connectYourWallet": "Conecte sua carteira",
    "contractDetails": "Detalhes dos contratos",
    "contracts": "Mercados",
    "contractsValue": "Valor dos contratos",
    "contractValue": "Valor dos contratos",
    "copySuccess": "Cópia bem-sucedida",
    "countdown": "Contagem regressiva",
    "cross": "Cruzar",
    "CROSS_DEPOSIT": "Depositar",
    "CROSS_WITHDRAW": "Sacar",
    "ORDER_INVALID_ORDER_SIDE": "Lado da ordem inválido. O lado da ordem é {{orderSide}}.",
    "crossChainTips": "Saques entre cadeias precisam de verificação em L2 (por comprovações ZK) e o processo de saque pode demorar até 2 horas. É necessário ter fundos suficientes no pool de ativos da cadeia correspondente para processar saques entre cadeias. Taxas de gás também serão incorridas. O ApeX Pro cobrará uma taxa para cobrir isso.",
    "crossFeeDesc": "Saques entre cadeias precisam de verificação em L2 (por comprovações ZK) e o processo de saque pode demorar até 2 horas. É necessário ter fundos suficientes no pool de ativos da cadeia correspondente para processar saques entre cadeias. Taxas de gás também serão incorridas. O ApeX Pro cobrará uma taxa para cobrir isso. Para saques sem taxas, faça saques normais no Ethereum (você terá que pagar as taxas de gás correspondentes e aguardar a confirmação em L2).",
    "dailyChange": "Variação em 24h",
    "dailyHigh": "Máxima de 24h",
    "dailyLow": "Mínima de 24h",
    "dailyTurnover": "Trades em 24h",
    "dailyTurnoverWithCoin": "Trades em 24h ({{coin}})",
    "dailyVolume": "Volume em 24h",
    "dailyVolumeWithCoin": "Volume em 24h ({{coin}})",
    "dayChange": "Variação em 24h",
    "dayTrades": "Trading em 24h",
    "Deposit": "Depositar",
    "deposit": {
        "success&check": "Depósito concluído, clique para visualizar ",
        "depositHistory": "histórico do depósito",
        "failed": "Falha no depósito"
    },
    "DEPOSIT": "Depositar",
    "depositAmountTips": "Valor de depósito necessário",
    "depositAndWithdraw": "Depositar e sacar",
    "depositConfirmationInfo": "Seu depósito <span class='active’>{{token}}</span> estará disponível após {{max}} confirmações.",
    "depositconfirmationProgress": " confirmações",
    "depositGaslessDesc": "Você atingiu o requisito mínimo de depósito de 1.000 USDC. O ApeX Pro cobrirá as taxas de gas deste depósito.",
    "depositing": "Depositando",
    "depositSuccess": "Depósito bem-sucedido",
    "depositSuccessInfo": "Depositar {{value}} {{coin}}",
    "depositSuccessTitle": "Depósito bem-sucedido",
    "depositWithToken": "Depositar {{token}}",
    "depth": "Profundidade",
    "dialogSlTips": "As ordens de stop-limit serão executadas quando {{price}} {{coin}} for atingido e o ganho esperado for de {{profit}} {{coin}}.",
    "dialogTpTips": "As ordens de stop-limit serão executadas quando {{price}} {{coin}} for atingido e o ganho esperado for de {{profit}} {{coin}}.",
    "dialogTrailingTips": "As ordens de stop-market serão executadas quando o preço ideal de mercado recuar para {{price}}.",
    "displayTrade": "Trading em 24h",
    "editShowItemTitle": "Mostrar itens",
    "emptyPositions": "Você não possui nenhuma posição.",
    "enableApexProWithToken": "Habilitar {{token}} no ApeX Pro",
    "enableApexWithToken": "Habilitar {{token}} no ApeX Pro",
    "enableSecureAccess": "Habilite o acesso seguro à API para fazer operações de trading extremamente rápidas.",
    "enableTokenDesc": "É necessário habilitar o {{Token}} ao realizar um depósito no ApeX Pro pela primeira vez. Só é necessário fazer isso uma vez.",
    "enableTrading": "Habilitar trading",
    "enableWithToken": "Habilitar {{token}}",
    "enterPrice": "Preço de entrada",
    "entryPrice": "Preço de entrada",
    "exchangeRateTips": "Obtenha a taxa de câmbio.",
    "exitByADL": "ADL",
    "exitByLiquidation": "Liquidação",
    "exitByTrade": "Trading",
    "exitPrice": "Preço de saída",
    "exitPriceDetailByADL": "Sua posição disparou a ADL.",
    "exitPriceDetailByLiquidate": "Sua posição disparou o preço de liquidação de {{liqPrice}}.",
    "exitType": "Tipo de saída",
    "expectedLiqPrice": "Preços de liquidação esperados",
    "EXPIRED": "Expirado",
    "Failed": "Falha",
    "FAILED_L2_REJECTED": "Rejeitado",
    "Fast": "Rápido",
    "FAST_WITHDRAW": "Saque rápido",
    "fastNoticeTips": "Com o Saque rápido, seu pedido será processado imediatamente e o ApeX Pro cobrará uma taxa para cobrir o custo de gas.",
    "fastWithdrawSuccess": "Saque rápido bem-sucedido",
    "Fee": "Taxa",
    "fee": "Taxa",
    "feeDesc": "Os saques rápidos são enviados imediatamente e o ApeX Pro cobrirá os custos de gas por uma taxa. Para saques sem taxas, faça saques lentos (você pagará seus próprios custos de gas e aguardará a confirmação da Camada 2).",
    "FILL_OR_KILL": "Fill-Or-Kill",
    "filled": "Executada",
    "FILLED": "Executada",
    "filledBuySuccessInfo": "Você adquiriu {{qty}} contratos {{token}} pelo preço de {{price}}.",
    "filledOTotal": "Executada/total",
    "filledPrice": "Preço executado",
    "filledSellSuccessInfo": "Você vendeu {{qty}} contratos {{token}} pelo preço de {{price}}.",
    "filledSuccessTitle": "Sua ordem foi totalmente executada.",
    "footer.copyright": "©2022 ApeX Todos os direitos reservados.",
    "footer.desc": "O ApeX é um protocolo de derivativos descentralizado, inovador e sem custódia que oferece aos traders de criptomoedas ferramentas financeiras transparentes que preservam e aumentam sua riqueza. Tenha acesso a uma experiência social de trading Web 3.0 incomparável para usuários individuais.",
    "footer.faqs": "FAQs",
    "footer.help.center": "Central de ajuda",
    "footer.join.our.discord": "Participe do nosso Discord",
    "footer.join.the.community": "Participe da nossa comunidade",
    "footer.nft": "NFTs",
    "footer.pool": "Reservas",
    "footer.product": "Produtos",
    "footer.support": "Suporte",
    "footer.trade": "ApeX Trade",
    "From": "De",
    "funding": "Financiamento",
    "fundingRate": "Taxa percentual de financiamento",
    "gaslessDepositsDesc": "Queda de depósitos sem gas <a>{{text}}</a>",
    "generateStarkKeyTips": "Gere sua StarkKey primeiro.",
    "GOOD_TIL_CANCEL": "Good-Till-Time",
    "gotIt": "Entendi",
    "hourFunding": "Financiamento em 1h",
    "IMMEDIATE_OR_CANCEL": "Immediate-Or-Cancel",
    "index.s2.desc": "Estamos constantemente lançando novos mercados de Contrato perpétuo.",
    "index.s2.title": "Comece a fazer trading",
    "index.s2.title.2": "Perpétuos",
    "index.s3.desc": "Crescimento contínuo com excelente liquidez e profundidade de mercado.",
    "index.s3.title": "Trading popular",
    "index.s3.title.2": "dados do mercado",
    "index.s4.desc": "Tecnologia líder e experiência com o produto",
    "index.s4.title": "Produto",
    "index.s4.title.2": "Apresentação",
    "index.s5.desc": "Tenha a experiência confiável ao seu lado e faça trading quando e onde quiser.",
    "index.s5.title": "Trading de Contratos perpétuos no ApeX Pro",
    "indexPrice": "Preço do índice",
    "informationTitle": "Informações",
    "installMetamask": "Instalar Metamask",
    "installWalletDesc": "Tente novamente depois de instalar a carteira no navegador.",
    "insufficientBalance": "Saldo insuficiente",
    "kline": "Preço",
    "KnowledgeCrossWithdraw": "FAQ sobre saque entre cadeias",
    "KnowledgeWithdraw": "FAQ sobre o saque rápido",
    "launchApp": "Abrir aplicativo",
    "layer2": "Layer 2",
    "layer2desc": "Desenvolvido na rede StarkWare Layer 2 no Ethereum, o contrato inteligente é de código aberto e verificado.",
    "lever.10": "Alavancagem 20X",
    "lever.desc": "Alavancagem máxima de 20X em trading de contrato perpétuo",
    "leverage": "Alavancagem",
    "limit": "Limite",
    "LIMIT": "Limite",
    "linkToBuy": "Não tem {{coin}}? Compre {{coin}} aqui.",
    "linkWalletTips": "Vincule sua carteira",
    "liqPrice": "Liq. Preço",
    "Liquidation": "Liquidação",
    "Liquidity": "Liquidez",
    "liquidityDesc": "Boa liquidez nos principais pares de moedas no mais alto nível.",
    "loading": "Carregando",
    "LONG": "Long",
    "marginMode": "Modo de margem",
    "markAllasRead": "Marcar todos como lido",
    "market": "Mercado",
    "MARKET": "Mercado",
    "marketContract": "Mercado",
    "marketPrice": "Preço de mercado",
    "markPrice": "Preço de referência",
    "MAX": "MÁX.",
    "maxWithdraw": "Limite de saque máx.",
    "maxWithdrawToken": "Valor de saque máx. de {{max}} {{token}}",
    "menu.back": "Voltar ao ApeX",
    "menu.copy": "Copiar endereço",
    "menu.Dashboard": "Painel",
    "menu.disconnect": "Desconectar",
    "menu.email": "Notificação por e-mail",
    "menu.email.desc": "Fique informado enquanto faz trading! Receba notificações por e-mail sobre mudanças no mercado, atividades da conta, atualizações de trading e muito mais.",
    "menu.find.password": "Recuperar chaves",
    "menu.home": "Início",
    "menu.setting": "Configurações",
    "menu.trade": "Trading",
    "multiChainKnowledge": "Saiba mais sobre depósitos e saques de ativos multicadeia.",
    "noData": "Nenhum registro encontrado",
    "noFundsTips": "Não há fundos ou registros de transações anteriores nesta carteira. Deposite fundos em sua carteira para prosseguir em sua jornada de integração.",
    "noMoreData": "Sem mais dados",
    "noNotifications": "Não há notificações.",
    "Normal": "Lento",
    "Notice": "Aviso",
    "noticeDesc": "Os saques normais são um processo de duas etapas. A etapa atual inicia a solicitação de saque e será processada na Camada 2. Quando os fundos estiverem prontos (pode demorar até 12 horas), você receberá uma notificação para sacar os fundos para a sua carteira. Você será responsável por quaisquer taxas de gas da transação.",
    "notifications": "Notificações",
    "onboradingTips": "Inicie a integração primeiro.",
    "onlyUnread": "Apenas não lidas",
    "OPEN": "Em aberto",
    "open.interests": "Posições em aberto",
    "open.interests.desc": "nas posições em aberto no ApeX Pro",
    "openInterest": "Posições em aberto",
    "openInterests": "Posições em aberto",
    "openLong": "Abrir Long",
    "openShort": "Abrir Short",
    "oraclePrice": "Preço oráculo",
    "order": "Ordem",
    "order.book.desc": "Parecido com o modo de trading do livro de ordens no CEXs e fácil de usar.",
    "orderBook": "Livro de ordens",
    "orderFailed": "A ordem falhou",
    "orderNo": "Nº da ordem",
    "orderPrice": "Preço da ordem",
    "orderRejected": "A ordem falhou, informe o preço novamente.",
    "orders": "Ordens",
    "orderTime": "Período da ordem",
    "orderType": "Tipo de ordem",
    "orderValue": "Valor da ordem",
    "overview": "Visão geral",
    "partiallyFilled": "Parcialmente executada",
    "past3Months": "Últimos 3 meses",
    "pastMonth": "Último mês",
    "pastWeek": "Última semana",
    "payment": "Pagamento",
    "PENDING": "Pendente",
    "PENDING_CENSORING": "Censura",
    "PENDING_L1_CREATING": "Pendente",
    "please.connect.wallet": "Conectar carteira",
    "please.onborading": "Finalize a integração primeiro.",
    "position": "Posição",
    "positionAllocation": "Alocação de posição",
    "positionMargin": "Margem da posição",
    "positions": "Posições",
    "POST_ONLY": "Post-Only",
    "postOnly": "Post-Only",
    "price": "Preço",
    "priceDistance": "Preço (distância)",
    "PrivacyPolicy": "Política de privacidade",
    "process.pending": "Pendente",
    "qty": "Quant.",
    "Rate": "Taxa",
    "recentTrades": "Trading recente",
    "Register": "Registrar",
    "rememberMe": "Lembrar-me",
    "resetGrid": "Redefinir layout",
    "retraceSpread": "Spread de retração",
    "rewards": "Prêmios",
    "riskLimits": "Limites de risco",
    "search": "Pesquisar",
    "selectMarket": "Selecionar mercado",
    "selectToken": "Selecionar token",
    "SELL": "Vender",
    "sellSuccessByLimitInfo": "{{qty}} contrato(s) {{token}} serão vendidos pelo preço de {{price}}.",
    "sellSuccessByMarketInfo": "{{qty}} contrato(s) {{token}} serão vendidos pelo preço de mercado.",
    "sellTpOSl": "Sell Short with TP/SL",
    "sendRequests": "Enviar solicitações",
    "setting": "Configurações",
    "SHORT": "Short",
    "showAllPositions": "Mostrar todas as posições",
    "side": "Lado",
    "signatureTips": "Você receberá duas solicitações de assinatura. A assinatura é gratuita e não disparará a transação.",
    "status": "Status",
    "STOP_LIMIT": "Limite condicional",
    "STOP_MARKET": "Mercado condicional",
    "stopLossWithCoin": "Parar a perda ",
    "submitFail": "O envio da ordem falhou",
    "submitSuccess": "Ordem enviada com sucesso",
    "SUCCESS": "Sucesso",
    "sure.pending": "Pendente",
    "Swap": "Troca",
    "swap.desc": "Quando um ativo não USDC é depositado, ele é automaticamente convertido em USDC pela API de 1 polegada.",
    "TAKE_PROFIT_LIMIT": "Limite condicional",
    "TAKE_PROFIT_MARKET": "Mercado condicional",
    "takeProfitWithCoin": "Tirar ganho {{coin}}",
    "TermsOfUse": "Termos de uso",
    "time": "Hora",
    "To": "Para",
    "toastInputPrice": "Insira o preço da ordem.",
    "toastInputQty": "Insira a quant. da ordem.",
    "toastInputTriggerPrice": "Insira o preço de disparo.",
    "toastNoAvailablePrice": "Sentimos muito, os preços não estão disponíveis.",
    "Total": "Total",
    "total": "Total",
    "totalAssets": "Patrimônio total",
    "totalEquity": "Patrimônio total",
    "tpOSL": "TP/SL",
    "tradeHistory": "Histórico de ordens",
    "tradeNo": "Nº da ordem de trading",
    "tradeNow": "Fazer trading agora",
    "tradeTime": "Período de trading",
    "tradeType": "Tipo de trading",
    "trading.desc": "executado nas últimas 24h",
    "trading.volume": "Volume de trading",
    "trading.volume.desc": "trocado nas últimas 24h",
    "tradings": "Tradings",
    "TRAILING_STOP": "Trailing-Stop",
    "trailingStop": "Trailing-Stop",
    "transaction": "TXID",
    "transfers": "Transferências",
    "triggerPrice": "Preço de disparo",
    "type": "Tipo",
    "typeFOK": "Fill-Or-Kill",
    "typeGTC": "Good Til Time",
    "typeIndex": "Índice",
    "typeIOC": "Immediate-Or-Cancel",
    "typeLast": "Último",
    "typeLastIndex": "Último preço do índice",
    "typeLastMark": "Último preço de referência",
    "typeLastPrice": "Último preço negociado",
    "typeMark": "Marcar",
    "UNKNOWN_ORDER_FILL_DIRECTION": "Desconhecido",
    "UNKNOWN_ORDER_SIDE": "Desconhecido",
    "UNKNOWN_ORDER_STATUS": "Desconhecido",
    "UNKNOWN_ORDER_TYPE": "Desconhecido",
    "unrealizedPnL": "P&L não realizado (%)",
    "UNTRIGGERED": "Não disparado",
    "value": "Valor",
    "verify.email": "Verificar e-mail",
    "verify.email.desc": "É necessário verificar seu endereço de e-mail para começar a receber notificações. Você pode alterar seu e-mail e configurações de notificações a qualquer momento no aplicativo.",
    "verifyOwnership": "Verificar propriedade",
    "Wallet": "Carteira",
    "walletAccess": "Habilite acesso à carteira.",
    "walletNotConnected": "Parece que sua carteira não está conectada!",
    "warnTitle": "Atenção",
    "welcomeBack": "Boas-vindas de volta! É necessário recuperar uma ou mais chaves.",
    "Withdraw": "Sacar",
    "withdraw": {
        "success": "Saque bem-sucedido"
    },
    "WITHDRAW": "Sacar",
    "withdraw.desc": "O processamento de saques normais pode demorar até 12 horas. Você será responsável pelas taxas de gas da transação. Use o saque rápido se precisar de acesso instantâneo aos fundos.",
    "withdraw.error": "Erro com o saque",
    "withdraw.fast.desc": "Uma taxa de {{fee}} será descontada por este saque. Seus fundos serão enviados imediatamente e estarão disponíveis na sua carteira assim que a transação for confirmada.",
    "withdrawAmount": "Valor do saque",
    "withdrawNotEnoughDesc": "A cadeia atual não atende às suas necessidades de saque. Alterne para outros tipos de cadeia que atendam à sua solicitação.",
    "withdrawRequestSuccess": "Solicitação de saque bem-sucedida",
    "withdrawSuccessInfo": "Sacar {{value}} {{coin}}",
    "withdrawSuccessTitle": "Saque bem-sucedido",
    "withdrawToWallet": "Solicitação de saque confirmada, saque para a carteira agora.",
    "withdrawWallet": "Sacar",
    "youWillReceive": "Você receberá",
    "goodTil": "Good Til",
    "reduceOnly": "Reduce-Only",
    "timeInForce": "Tempo em vigor",
    "weekWithNum": "{{num}} sem.",
    "dayWithNum": "{{num}} d",
    "hourWithNum": "{{num}} h",
    "yes": "Sim",
    "no": "Não",
    "rememberMeDesc": "Somente use a função 'Lembrar-me' quando usar um dispositivo seguro que seja seu. Selecionar essa opção poderá expor suas chaves e informações a outras pessoas se você estiver usando um dispositivo público ou sem segurança.",
    "allTradeHistory": "Histórico completo de trading",
    "settings.accountDesc": "Atualizações sobre a conta, depósitos e saques",
    "settings.Trading": "Trading",
    "settings.TradingDesc": "Atualizações sobre ordens e liquidações",
    "acknowledgeTerms": "Reconhecimento dos termos",
    "acknowledge.purpose": "Para cumprir as políticas nacionais ou regionais relevantes, você concorda e assegura que:",
    "acknowledge.desc1": "Você não é uma pessoa ou empresa residente ou localizada, incorporada ou com agente registrado nos Estados Unidos ou em um local sob restrição.",
    "acknowledge.desc2": "Você não acessará este site ou fará trading no ApeX Pro enquanto estiver nos Estados Unidos ou em um local sob restrição.",
    "acknowledge.desc3": "Você não está usando e não usará uma VPN para mascarar sua localização física a partir de um local sob restrição.",
    "btn.agree": "Eu concordo",
    "acknowledge.TermsAndPrivacy": "Ao fazer trading no ApeX Pro, você concorda com os {{TermsOfUse}} e {{PrivacyPolicy}}.",
    "tryAgain": "Tentar novamente",
    "fastWithdrawFee": "Taxa de saque rápido",
    "withdrawFee": "Taxa de saque",
    "availableDesc": "Valor máx. que pode ser sacado. Não será possível realizar saques quando o valor disponível mostrado for negativo ou igual a 0.",
    "MaxSlippage": "Adiamento máximo",
    "1HRatio": "Taxa 1h",
    "8HRatio": "Taxa 8h",
    "annualized": "Anual",
    "faucet": {
        "claim": {
            "success": "Reivindicado com sucesso, verifique sua carteira mais tarde.",
            "failure": "Falha ao reivindicar, tente novamente mais tarde."
        }
    },
    "Claim": "Reivindicar",
    "INVALID_L2_SIGNATURE": "Assinatura L2 inválida.",
    "INVALID_OFFSET_DATA": "Dados de compensação inválidos. Os dados de compensação são {{offsetData}}.",
    "INVALID_LP_ACCOUNT": "Conta LP inválida. A ID da conta é {{accountId}}.",
    "INVALID_FEE": "Parâmetro de taxa inválido. Os dados de taxa são {{fee}}.",
    "INVALID_USER_ID": "ID de usuário inválida. A ID de usuário é {{userId}}.",
    "INVALID_ACCOUNT_ID": "ID de conta inválida. A ID da conta é {{accountId}}.",
    "INVALID_CURRENCY_ID": "ID de token inválida. A ID de token é {{currencyId}}.",
    "INVALID_CLIENT_WITHDRAW_ID": "ID de saque do cliente inválida. A ID de saque do cliente é {{clientWithdrawId}}.",
    "INVALID_DECIMAL_SCALE_PARAM": "Nome inválido ‘{{name}}’, valor ‘{{decimalStr}}’ e tamanho da etapa ‘{{stepSize}}’.",
    "EMPTY_CHAIN_ID": "Parâmetro de ID de cadeia vazio. Preencha-o.",
    "EMPTY_CLIENT_FAST_WITHDRAW_ID": "ID de saque rápido do cliente vazia.",
    "ACCOUNT_NOT_FOUND_LP": "Conta LP não encontrada. A ID da conta LP é {{lpAccountId}}.",
    "ACCOUNT_CONFLICT_L2KEY": "Conflito de chave L2 da conta.",
    "ORDER_NOT_FOUND": "Ordem não encontrada. A ID da ordem é {{orderId}}.",
    "ORDER_INVALID_TIME_IN_FORCE": "Time-in-force da ordem inválido. O time-in-force é {{timeInForce}}.",
    "ORDER_INVALID_STATUS": "Status da ordem inválido. O status da ordem é {{orderStatus}}.",
    "ORDER_DELEVERAGE_WITH_SAME_ACCOUNT": "Desalavancagem na mesma conta.",
    "CROSS_DEPOSIT_CURRENCY_ID_AMOUNT_CHANGED": "A ID e o valor do token de depósito não Ethereum foram alterados. A ID de token é {{currencyId}} e o valor é {{amount}}.",
    "CROSS_WITHDRAW_GREETER_MAX_ABLE_AMOUNT": "O valor de saque não Ethereum é maior que o valor máximo de saque disponível.",
    "FAST_WITHDRAW_ID_NOT_FOUND": "A ID de saque rápido não foi encontrada. A ID de saque é {{withdrawId}}.",
    "DEPOSIT_AMOUNT_INVALID": "O valor do depósito de Ethereum é inválido. O valor é {{amount}}.",
    "DEPOSIT_CENSOR_ROUND_CONFLICT": "Conflito na rodada do censurador de depósito de Ethereum. A rodada de censurador é {{censorRound}}.",
    "typeOpenShort": "Vender",
    "Filled_lost": "Este pedido foi cancelado porque foi rejeitado na cadeia. Seus ativos não serão perdidos. Envie um pedido novamente.",
    "Post-Only2": "O pedido Post-Only será executado apenas como um pedido do maker. Se puder ser executado imediatamente como um pedido do beneficiário, ele será automaticamente cancelado.",
    "FundingRate1": "As tarifas de financiamento serão intercambiadas entre titulares de posições long e short a cada 1 hora. Note que a taxa de financiamento irá flutuar em tempo real a cada 1 hora. Se a taxa de financiamento for positiva na liquidação, os titulares de posições long pagarão aos titulares de posições short. Se a taxa de financiamento for negativa, os titulares de posições short pagarão aos titulares de posições long. O valor de sua posição no momento em que o financiamento for estabelecido será usado para calcular suas tarifas de financiamento. Tarifas de financiamento = Tamanho da posição*Preço do índice*Taxa de financiamento",
    "ORDER_POSSIBLE_GREATER_THAN_SYMBOL_MAX_POSITION": "Se a ordem for executada, ela poderá ser maior que o tamanho máximo da posição ‘{{symbol}}’. O tamanho máximo da posição é {{maxPositionSize}}.",
    "ORDER_IS_LIQUIDATE_NOT_MATCH_PRE_CONDITION": "A ordem de liquidação não atende à condição prévia: BeforeTV({{beforeTV}}) < BeforeTR({{beforeTR}}).",
    "ORDER_THERE_IS_NOT_ENOUGH_MARGIN_TO_OPEN_POSITION": "Se a ordem for executada, não haverá margem suficiente para abrir uma posição.",
    "Setup": "Configurar",
    "incorrectEmail": "O e-mail está incorreto.",
    "ORDER_LIMIT_FEE_NOT_ENOUGH": "A taxa de limite da ordem é insuficiente. A taxa limite é {{limitFee}}.",
    "ORDER_FILL_TRANSACTION_ID_NOT_FOUND": "Este pedido não existe.",
    "Account": "Conta",
    "allFilled": "Todas executadas",
    "allClosePnl": "Todos P&L fechados",
    "Equity": "Patrimônio",
    "Fast withdraw": "Saque rápido",
    "minDeposit": "Depósito mín. de {{amount}} {{token}}",
    "minWithdraw": "Saque mín. de {{amount}} {{token}}",
    "viewWalletConenctHelp": "Veja o manual de conexão da carteira aqui.",
    "Optional": "Opcional",
    "Username": "Nome de usuário",
    "Email": "E-mail",
    "Unverified": "Não verificado",
    "Verified": "Verificado",
    "General": "Geral",
    "settings.generalDesc": "Newsletter, atualizações sobre o mercado e produtos",
    "ORDER_FILL_TRANSACTION_CENSOR_ROUND_CONFLICT": "Conflito de dados da rodada de verificação de transações em {{censorRound}}.",
    "ORDER_FILL_TRANSACTION_INVALID_STATUS": "O status da transação de execução da ordem é inválido. O status da transação é {{transactionStatus}}.",
    "ORDER_EMPTY_CLIENT_ORDER_ID": "ID da ordem de cliente vazia.",
    "ORDER_INVALID_CLIENT_ORDER_ID": "ID da ordem de cliente inválida. A ID da ordem do cliente é {{clientOrderId}}.",
    "ORDER_LIQUIDATE_ORDER_FAILED": "A criação da ordem de liquidação falhou.",
    "ORDER_CLIENT_ORDER_DATA_CONFLICT": "Dados gerados durante a criação da ordem entram em conflito com a ID da ordem do cliente. A ID da ordem do cliente é {{clientOrderId}}.",
    "ORDER_PRICE_MUST_GREETER_ZERO": "O preço da ordem deve ser maior que 0. O preço da ordem é {{price}}.",
    "ORDER_SIZE_MUST_GREETER_ZERO": "O tamanho da ordem deve ser maior que 0. O tamanho da ordem é {{size}}.",
    "ORDER_VALUE_MUST_GREETER_ZERO": "O valor da ordem deve ser maior que 0. O valor da ordem é {{value}}.",
    "ORDER_LIMIT_FEE_MUST_GREETER_ZERO": "A taxa limite deve ser maior que ou igual a 0. A taxa limite é {{limitFee}}.",
    "ORDER_TRIGGER_PRICE_MUST_GREETER_ZERO": "O preço de disparo da ordem deve ser maior que 0. O preço de disparo é {{triggerPrice}}.",
    "CROSS_DEPOSIT_DATA_ERROR": "Erro de dados de depósito não Ethereum.",
    "CROSS_WITHDRAW_WALLET_BALANCE_NOT_ENOUGH": "O saque não Ethereum não tem saldo da carteira suficiente.",
    "CROSS_WITHDRAW_DATA_ERROR": "Erro de dados de saque não Ethereum.",
    "CROSS_WITHDRAW_ID_NOT_FOUND": "ID de saque não Ethereum não encontrada. A ID de saque é {{withdrawId}}.",
    "CROSS_WITHDRAW_INVALID_STATUS": "Status de saque não Ethereum inválido. O status é {{status}}.",
    "CROSS_WITHDRAW_RISK_CHECK_FAILED": "A verificação de risco de saque não Ethereum falhou.",
    "CROSS_WITHDRAW_INVALID_ARGUMENT": "Parâmetros de saque não Ethereum inválidos.",
    "FAST_WITHDRAW_DATA_ERROR": "Erro de dados de saque rápido.",
    "FAST_WITHDRAW_GREETER_MAX_ABLE_AMOUNT": "O valor de saque rápido é maior que o valor máximo de saque disponível.",
    "FAST_WITHDRAW_RISK_CHECK_FAILED": "A verificação de risco de saque rápido falhou.",
    "FAST_WITHDRAW_INVALID_ARGUMENT": "Argumento de saque rápido inválido.",
    "FAST_WITHDRAW_INVALID_STATUS": "Status de saque rápido inválido. O status é {{status}}.",
    "DEPOSIT_ASSET_ID_INVALID": "A ID de ativo de depósito de Ethereum é inválida. A ID de ativo é {{assetId}}.",
    "DEPOSIT_ASSET_ID_AMOUNT_CHANGED": "O valor e a ID de ativo do depósito de Ethereum foram alterados. A ID de ativo é {{assetId}}, o valor é {{amount}}.",
    "DEPOSIT_STATUS_INVALID": "O status do depósito de Ethereum é inválido. O status é {{status}}.",
    "DEPOSIT_ID_NOT_FOUND": "Erro de dados! ID de depósito incorreta.",
    "WITHDRAW_INVALID_ARGUMENT": "Conflito de dados de saque do cliente.",
    "WITHDRAW_WALLET_BALANCE_NOT_ENOUGH": "Falha no saque de Ethereum, saldo da carteira insuficiente.",
    "InvalidParameters": "Parâmetros inválidos",
    "GoodTil1": "Após o tempo de expiração, o pedido será automaticamente cancelado.",
    "verify": {
        "back": "Voltar ao trading",
        "mail": {
            "resendTitle": "Confirmar endereço de e-mail",
            "resend": "Reenviar e-mail de confirmação →",
            "resendDesc": "Clique no link do e-mail que enviamos para confirmar a propriedade de seu endereço de e-mail.",
            "success": "Envio bem-sucedido",
            "failure": "Falha ao enviar"
        },
        "expired": "O link de confirmação por e-mail expirou"
    },
    "today": "Hoje",
    "Reduce-Only1": "O pedido Reduce-Only reduzirá apenas o tamanho de sua posição. Qualquer pedido que possa aumentar o tamanho de sua posição será cancelado ou ajustado.",
    "Leverage1": "A alavancagem efetiva é calculada pelo valor da posição atual / ativos totais.",
    "OraclePrice1": "O preço do oráculo extrai dados de um prestador de serviços de nó externo independente, que é usado para calcular seu preço de liquidez e margem de posição.",
    "Liq": {
        " Price1": "Seu preço estimado de liquidação é afetado pela alavancagem e pela margem. A posição será liquidada quando o preço do oráculo atingir o preço de liquidação."
    },
    "Unrealized P&L1": "Lucro/perda não realizado e retorno desta posição",
    "typeOpenLong": "Comprar",
    "ADL1": "As luzes indicam sua prioridade ADL na fila. Cada luz representa um incremento de 20% para o próximo percentual. Se todas as luzes estiverem acesas, sua posição está no percentual acima.",
    "TimeinForce1": "O Tempo de vigência inclui: Post-Only, Good-Til-Time, Immediate-Or-Cancel, Fill-Or-Kill.",
    "ORDER_SYMBOL_DISABLE_TRADE": "Não há suporte a transações para o símbolo ‘{{symbol}}’.",
    "Connected": "Conectada",
    "ORDER_LIQUIDATING_ACCOUNT_CANNOT_CREATE_ORDER": "A conta está sendo liquidada. Não é possível criar uma ordem.",
    "Connecting": "Conectando",
    "ORDER_SYMBOL_DISABLE_OPEN_POSITION": "No momento, você não pode abrir novas posições para o contrato {{symbol}}.",
    "ORDER_IS_REDUCE_ONLY_CANNOT_OPEN_POSITION": "A ordem é do tipo Reduce-Only. Não é possível abrir uma nova posição.",
    "ORDER_IS_LIQUIDATE_ONLY_CANNOT_OPEN_POSITION": "O pedido foi liquidado, não é possível abrir uma nova posição.",
    "ORDER_IS_DELEVERAGE_ONLY_CANNOT_OPEN_POSITION": "Seu pedido será desalavancado automaticamente. Não é possível abrir uma nova posição.",
    "ORDER_IS_LIQUIDATE_AND_DELEVERAGE_NOT_MATCH_PRE_CONDITION": "As ordens de liquidação e desalavancagem não atendem à condição prévia: BeforeTV({{beforeTV}}) < 0.",
    "ORDER_POSSIBLE_LEAD_TO_ACCOUNT_LIQUIDATED": "Se a ordem for executada, sua conta poderá ser liquidada.",
    "ORDER_POSSIBLE_LEAD_TO_ACCOUNT_LIQUIDATED_TV_TR_RATE_NOT_IMPROVED": "Se a ordem for executada, sua conta poderá ser liquidada. O TV/TR não aumentará depois que a ordem for executada.",
    "ORDER_SIZE_SMALLER_THAN_SYMBOL_MIN_ORDER_SIZE": "O tamanho da ordem {{size}} é menor que o tamanho mínimo da ordem {{symbol}}. O tamanho mínimo da ordem é {{minOrderSize}}.",
    "ORDER_WITH_THIS_PRICE_CANNOT_REDUCE_POSITION_ONLY": "A ordem com este preço {{price}} não pode ser do tipo Reduce-Only.",
    "ORDER_SIZE_GREATER_THAN_SYMBOL_MAX_ORDER_SIZE": "O tamanho da ordem {{size}} é maior que o tamanho máximo da ordem {{symbol}}. O tamanho máximo da ordem é {{maxOrderSize}}.",
    "ORDER_OPEN_ORDER_COUNT_LIMIT_EXCEED": "Você tem {{openOrderCount}} ordens em aberto e não é possível criar novas ordens.",
    "usernametips": "A combinação deve ter de 4 a 20 letras, números ou sublinhados.",
    "usernameistaken": "Este nome de usuário já foi usado.",
    "FailedToConnect": "Falha ao conectar",
    "operate": "Operate",
    "details": "Detalhes",
    "banner": {
        "view": "Visualizar"
    },
    "Details": {
        "Market": "Mercado",
        "MaximumLeverage": "Alavancagem máxima",
        "InitialMarginFraction": "Fração de margem inicial",
        "MaintenanceMarginFraction": "Fração de margem de manutenção",
        "IncrementalInitialMarginFraction": "Fração de margem inicial incremental",
        "TickSize": "Tamanho do tick",
        "StepSize": "Tamanho da etapa",
        "MinimumOrderSize": "Tamanho mínimo do pedido",
        "MaximumOrderSize": "Tamanho máximo do pedido",
        "BaselinePositionSize": "Tamanho da posição de base",
        "IncrementalPositionSize": "Tamanho de posição incremental",
        "MaximumPositionSize": "Tamanho máximo de posição"
    },
    "priceWithType": "Preço({{type}})",
    "amountWithType": "Quantia({{type}})",
    "totalWithType": "Total({{type}})",
    "crossLong": "Long",
    "crossShort": "Short",
    "statusActive": "Ativo",
    "January": "Janeiro",
    "March": "Março",
    "April": "Abril",
    "June": "Junho",
    "July": "Julho",
    "September": "Setembro",
    "October": "Outubro",
    "November": "Novembro",
    "December": "Dezembro",
    "Jan": "Jan.",
    "Feb": "Fev.",
    "Mar": "Mar.",
    "Apr": "Abr.",
    "May": {
        "little": "Maio",
        "big": "Maio"
    },
    "Jun": "Jun.",
    "Jul": "Jul.",
    "Aug": "Ago.",
    "Sep": "Set.",
    "Oct": "Out.",
    "Nov": "Nov.",
    "Dec": "Dez.",
    "Monday": "Segunda",
    "Tuesday": "Terça",
    "Wednesday": "Quarta",
    "Thursday": "Quinta",
    "Friday": "Sexta",
    "Sat": "Sáb.",
    "Sun": "Dom.",
    "Mon": "Seg.",
    "Tue": "Ter.",
    "Thu": "Qui.",
    "Fri": "Sex.",
    "February": "Fevereiro",
    "August": "Agosto",
    "Saturday": "Sábado",
    "Sunday": "Domingo",
    "Wed": "Qua.",
    "login": {
        "scan": {
            "dialogTitle": "Acesso ao aplicativo",
            "title": "Digitalize o QR Code para entrar no aplicativo",
            "desc": "Após instalar o aplicativo ApeX Pro, você pode fazer o login com seu celular sem a necessidade de instalar uma carteira. Não compartilhe seu QR Code exclusivo.",
            "qrcodeDisplay": "Clique para visualizar",
            "offline": "Sua conexão com a internet está instável. Verifique sua rede e digitalize o código novamente."
        }
    },
    "VERIFY_EMAIL_TOO_MANY_REQUESTS": "Mais de uma solicitação de API de chamada por minuto feita. Diminua a velocidade.",
    "USER_NOT_FOUND": "Usuário não encontrado.",
    "INVALID_COUNTRY_CODE": "Código de país inválido.",
    "INVALID_USER_NICKNAME": "O apelido inserido é inválido.",
    "EMAIL_VERIFY_LINK_EXPIRED": "O link de verificação de e-mail venceu.",
    "DEVICE_DOES_NOT_EXISTS": "A ID do dispositivo não existe.",
    "EMAIL_VERIFY_FAILED": "A verificação de e-mail falhou.",
    "SetDoneTips": "Modificação concluída",
    "PofitToday": "Ganho hoje",
    "PofitTodayTips": "Incremento no lucro total desde 12 am (meia-noite) UTC hoje, excluindo depósitos e saques",
    "TooFrequentReject": "Muito frequente, rejeite.",
    "share": {
        "twitter": {
            "desc": "Acabei de fazer um trading no ApeX Pro! Obtenha acesso a um DEX de derivativos de alto desempenho para uma experiência de trading atualizado hoje."
        },
        "shareActivity": "Compartilhar atividade",
        "imgSize": "Tamanho",
        "download": "Baixar",
        "copy&share": "Copiar e compartilhar"
    },
    "closeQuantity": "Quantidade do fechamento",
    "closeByMarket": "Fechamento do mercado",
    "withdrawzerotips": "Você já fez um saque ou os fundos disponíveis são 0, não há necessidade de iniciar um saque.",
    "marketclosenotmatchtips": "Não foi possível encontrar nenhuma cotação para o fechamento do seu pedido (mercado)",
    "Fees": "Tarifas",
    "cancelFromOBTips": "Clique para cancelar {{count}} pedido(s) ativo(s) nesse preço",
    "cancelFromOBSuccess": "Todos os {{count}} pedidos ativos foram cancelados.",
    "viewBigImage": "Clique para ampliar a imagem.",
    "tabFunding": "Taxa de financiamento",
    "availableMarginTips": "Margem máxima atual da conta",
    "leverageTips": "O valor atual de todas as posições na conta/patrimônio total da conta",
    "contractValueTips": "O valor total de todas as posições na conta",
    "SlippageSetting": "Configurações de adiamento",
    "Swap & Deposit": "Troca e depósito",
    "toastTitleSuccess": "Sucesso",
    "toastTitleWarn": "Atenção",
    "toastTitleFail": "Falha",
    "toastTitleTips": "Dicas",
    "orderCancelSuccess": "Cancelamento bem-sucedido",
    "seeDetails": "Ver detalhes",
    "guide": {
        "walletTitle": "Conecte sua carteira",
        "walletTips": "Conecte sua carteira e continue para verificá-la.",
        "depositTips": "Faça um depósito antes de começar a fazer trading.",
        "closePositionTitle": "Fechar por preço de limite",
        "nextBtn": "Próximo",
        "backBtn": "Voltar",
        "doneBtn": "Concluído",
        "tradeTitle": "Selecionar o tipo de pedido adequado",
        "tradeTips": "O pedido limitado será negociado ao preço desejado, o pedido de mercado será negociado imediatamente ao preço de mercado, e o pedido condicional será acionado após o preço que você estabelece ser alcançado.",
        "depositTitle": "Depósito em conta",
        "closePositionTips": "Clique no botão para fechar a posição no preço de limite."
    },
    "Success": "Sucesso",
    "trade": {
        "crossTips": "O APEX Pro oferece a você até {{cross}}X de alavancagem disponível para fazer trading dos contratos atuais; a alavancagem efetiva das suas posições dependerá do valor da sua posição e do patrimônio total.",
        "ipLimit": "Seu endereço IP não está dentro da zona de serviço do ApeX Pro. Segundo os Termos de Serviço do ApeX Pro, o ApeX Pro não está disponível no seu país/região."
    },
    "menu": {
        "airdrop": "Airdrop",
        "mining": "Mineração",
        "referral": "Indicação",
        "taskcenter": "centro de tarefas",
        "staking": "Staking",
        "apiCenter": "Central API",
        "mvpTrading": "MVP Contest"
    },
    "connect": {
        "welcome": "Boas-vindas de volta!",
        "recover": "É necessário recuperar uma ou mais chaves."
    },
    "buyTpOSl": "Buy Long with TP/SL",
    "ethmergetips": "Please note that there will be a delay in processing all deposits to ApeX Pro via the Ethereum chain due to the Eth2 merge. Once the Eth2 upgrade is complete and stable, your deposits will then be fully processed and reflected in your account. For the estimated processing time, please check ApeX Pro's announcements. You are advised to make your deposits accordingly to account for possible delays.",
    "page403Title": "Acesso negado",
    "page403Description": "Infelizmente, você não tem as permissões para acessar esta página.",
    "rewardCenter": {
        "Date": "Data",
        "bigCaseToday": "HOJE",
        "popularCampaigns": "Campanhas populares",
        "joinedCampaign": "Você está participando desta campanha!",
        "claimMoreRewards": "Você pode resgatar prêmios para {{x}} campanhas!",
        "Rewards": "Prêmios",
        "APEXREWARDSBanner": "PRÊMIOS DO APEX",
        "descriptionAPEXREWARDSBanner": "Acesse todas as últimas promoções e ofertas do ApeX Pro para obter grandes ganhos hoje mesmo.",
        "bigCaseConnectWallet": "CONECTAR CARTEIRA",
        "TotalRewards": "Prêmios totais",
        "ClaimedRewards": "Prêmios resgatados",
        "UnclaimedRewards": "Prêmios não resgatados",
        "TradeToEarnRewards": "Prêmios do evento “Faça trading e ganhe”",
        "totalRewardsDescription": "A quantidade total de prêmios resgatados e não resgatados.",
        "claimedRewardsDescription": "A quantidade total de prêmios resgatados com sucesso.",
        "unclaimedRewardsDescription": "A quantidade total de prêmios não resgatados.",
        "longTermCampaigns": "Campanhas de longo prazo",
        "All": "Todas",
        "Ended": "Encerradas",
        "Ongoing": "Em andamento",
        "Upcoming": "Futuras",
        "Joined": "Participando",
        "emptyCalendarDescription": "Não há campanhas na data selecionada. Confira outras datas!",
        "emptyPopularDescription": "Campanhas novas e exclusivas serão lançadas em breve. Fique atento! ",
        "campaignsEndedError": "Esta campanha já foi encerrada. Confira outras campanhas!",
        "shareRewordsDescription": "Ganhei um total de {{amount}} {{coin}} em prêmios. Ganhe mais prêmios comigo agora mesmo!",
        "Claimed": "Resgatado",
        "ViewMore": "Ver mais",
        "Join": "Participar"
    },
    "Rewards": "Prêmios",
    "APEXREWARDSBanner": "PRÊMIOS DO APEX",
    "descriptionAPEXREWARDSBanner": "Acesse todas as últimas promoções e ofertas do ApeX Pro para obter grandes ganhos hoje mesmo.",
    "bigCaseConnectWallet": "CONECTAR CARTEIRA",
    "TotalRewards": "Prêmios totais",
    "ClaimedRewards": "Prêmios resgatados",
    "TradeToEarnRewards": "Prêmios do evento “Faça trading e ganhe”",
    "totalRewardsDescription": "A quantidade total de prêmios resgatados e não resgatados.",
    "claimedRewardsDescription": "A quantidade total de prêmios resgatados com sucesso.",
    "popularCampaigns": "Campanhas populares",
    "longTermCampaigns": "Campanhas de longo prazo",
    "All": "Todas",
    "Ended": "Encerradas",
    "Ongoing": "Em andamento",
    "Upcoming": "Futuras",
    "Joined": "Participando",
    "emptyCalendarDescription": "Não há campanhas na data selecionada. Confira outras datas!",
    "emptyPopularDescription": "Campanhas novas e exclusivas serão lançadas em breve. Fique atento! ",
    "shareRewordsDescription": "Ganhei um total de {{amount}} {{coin}} em prêmios. Ganhe mais prêmios comigo agora mesmo!",
    "Claimed": "Resgatado",
    "ViewMore": "Ver mais",
    "Join": "Participar",
    "joinedCampaign": "Você está participando desta campanha!",
    "claimMoreRewards": "Você pode resgatar prêmios para {{x}} campanhas!",
    "Date": "Data",
    "bigCaseToday": "HOJE",
    "UnclaimedRewards": "Prêmios não resgatados",
    "unclaimedRewardsDescription": "A quantidade total de prêmios não resgatados.",
    "campaignsEndedError": "Esta campanha já foi encerrada. Confira outras campanhas!",
    "choosenetwork": "Escolha a rede",
    "choosenetwork2": "Você pode se conectar a qualquer uma das redes compatíveis abaixo para fazer um depósito.",
    "choosewallet": "Escolha a carteira ",
    "sl_type": "Pedido  SL (mercado)",
    "ORDER_TAKE_PROFIT_STOP_LOSS_ONLY_SUPPORT_MARKET_PRICE": "As ordens de Take-Profit e de Stop-Loss somente oferecem suporte para ordens de mercado.",
    "revoke": "Cancelar",
    "revokeAll": "Cancelar tudo",
    "add": "Adicionar",
    "revokeOrder": "Cancelar pedido",
    "revokeAllTpOSlTips": "Confirme que deseja cancelar todos os pedidos TP/SL.",
    "detailsTP": "Tirar ganho:",
    "detailsSL": "Parar a perda:",
    "createSuccessTitle.tpOSl": "Pedido enviado com sucesso",
    "createSuccessTips.tpOSl": "TP/SL definido com sucesso",
    "cacelSuccessTitle.tpOSl": "Pedido cancelado",
    "cacelSuccessTips.tpOSl": "TP/SL cancelado",
    "tpPriceTips.tpOSl": "Insira o preço de TP",
    "tpVolumeTips.tpOSl": "Insira a quantidade de TP",
    "slPriceTips.tpOSl": "Insira o preço de SL",
    "tpPriceLessTips.tpOSl": "O Preço de TP deve ser maior do que o Último preço.",
    "tpPriceMoreTips.tpOSl": "O Preço de TP deve ser menor do que o Último preço.",
    "slPriceLessTips.tpOSl": "O Preço de SL deve ser maior do que o Último preço.",
    "tpPriceLessWithPositionTips.tpOSl": "O Preço de TP deve ser maior do que o Preço de entrada.",
    "tpPriceMoreWithPositionTips.tpOSl": "O Preço de TP deve ser menor do que o Preço de entrada.",
    "slPriceMoreWithPositionTips.tpOSl": "O Preço de SL deve ser menor do que o Preço de entrada.",
    "slPriceLessWithPositionTips.tpOSl": "O Preço de SL deve ser maior do que o Preço de entrada.",
    "slPriceLessWithLiqTips.tpOSl": "O preço de SL não corresponde ao preço de liquidação forçada. Insira novamente.",
    "ORDER_TAKE_PROFIT_STOP_LOSS_REDUCE_ONLY_MUST_BE_TRUE": "Ao adicionar uma ordem de Stop-Loss, o parâmetro Reduce-Only deve ser verdadeiro.",
    "ORDER_TAKE_PROFIT_MARKET_ORDER_NUM_EXCEEDS_MAX_VALUE": "Ordem TP: A quantidade da ordem excedeu o tamanho máximo. O tamanho máximo é {{maxSize}}.",
    "ORDER_STOP_MARKET_ORDER_NUM_EXCEEDS_MAX_VALUE": "Ordem SL: A quantidade da ordem excedeu o tamanho máximo. O tamanho máximo é {{maxSize}}.",
    "feeTips": {
        "filled": "Taxas = Taxas de transação de negociação + Taxas de liquidação",
        "closePnL": "Taxas = Taxas incorridas para abrir uma posição + Taxas incorridas para fechar uma posição + Taxas de liquidação"
    },
    "riskRate": "Limite de risco",
    "riskValue": {
        "trade": "Valor da posição "
    },
    "initialMarginRate": {
        "trade": " Taxa de margem inicial"
    },
    "maintenanceMarginRate": {
        "trade": " Taxa de margem de manutenção"
    },
    "maxLeverage": {
        "trade": "alavancagem"
    },
    "initialMargin": {
        "trade": "Margem inicial"
    },
    "maxPositionLeverage": {
        "trade": "Alavancagem de posição máxima"
    },
    "slAvailableVolume": "Máx. de pedidos SL ",
    "tpAvailableVolume": "Máx. de pedidos TP ",
    "maintenanceMargin": {
        "trade": "Margem de manutenção\n"
    },
    "tp_type": "Pedido TP (mercado) ",
    "openFee": {
        "trade": "Taxa para abrir uma posição "
    },
    "closeFee": {
        "trade": "Taxa para fechar uma posição "
    },
    "liqFee": {
        "trade": "Taxa de liquidação "
    },
    "lastPrice": "Último preço",
    "contractVolume": "QTD",
    "id": "Nº",
    "tradeFee": {
        "trade": "Corretagem"
    },
    "takeProfit": "TP",
    "stopLoss": "SL",
    "slVolumeTips.tpOSl": "Insira a quantidade de SL",
    "slPriceMoreTips.tpOSl": "O Preço de SL deve ser menor do que o Último preço.",
    "menu.rewardCenter": "Prêmios",
    "tradeToMine": {
        "descrTotalSwapped": "O Total trocado é a soma de USDC ganho ao vender BANA por meio de uma reserva de BANA-USDC.",
        "descrTotalRedeemed": "O Total resgatado é a quantia total de APEX resgatada com BANA.",
        "formula2Detail1": "θ: o valor de θ na 1ª época é zero. A partir da 2ª época, o valor de θ será ajustado a cada 4 épocas, e estará sujeito a alterações durante esse período.",
        "UnreleasedRewards": "Recompensas não lançadas da última Época (BANA)",
        "Confirm": "Confirmar",
        "descrTotalClaimed": "O Total reivindicado é a quantia total de BANA reivindicada durante o evento “Faça trading e ganhe”.",
        "AddLiquidity": "Adicionar",
        "RemoveLiquidity": "Remover liquidez",
        "StartingSoon": "Começa em breve",
        "myEstReward": "Minha recompensa estimada",
        "AvgLP": "Média Retenções de token LP",
        "AffiliateCommission": "Comissões",
        "formula2Detail2": "Para outros parâmetros e fórmulas, o ApeX Pro pode fazer pequenos ajustes de acordo com as circunstâncias do evento. Siga as contas das redes sociais relacionadas ao ApeX Pro ou vincule seu endereço de e-mail à sua conta do ApeX Pro para receber as atualizações mais recentes.",
        "BBPGitBook": "confira mais informações.",
        "titleTWAMMPool": "Reserva de liquidez de BANA-USDC",
        "descrTWAMMPool": "A reserva de liquidez de BANA-USDC usa trocas de TWAMM. Quando o evento “Faça trading e ganhe” começar, os traders podem comprar ou vender BANA na reserva. A reserva de Compra e Venda (BBP) do ApeX Pro prosseguirá com recompras de longo prazo de BANA por meio da reserva de liquidez. Para mais informações, confira a visão geral da BBP.",
        "LP": "Token LP",
        "descrLP": "Você receberá token(s) LP por reter seus BANA ou USDC na reserva de liquidez de BANA-USDC. Quanto mais tokens LP você tiver, mais BANA você ganhará no total.",
        "price": "Valor de BANA (USDC)",
        "PooledBANA": "BANA reservado",
        "PooledUSDC": "USDC reservado",
        "shareOfPool": "Parte da reserva",
        "ManageLiquidity": "Gerenciar liquidez",
        "descrRedeemRate": "Taxa de resgate refere-se à taxa de conversão entre tokens BANA e APEX após o término da última época do evento “Faça trading e ganhe”, ou seja, a quantia de APEX resgatada para 1 BANA.",
        "Add": "Adicionar",
        "Remove": "Remover",
        "Balance": "Saldo",
        "YouWillReceive": "Você receberá",
        "Approve": "Aprovar {{tokenName}}",
        "errorInsufficient": "Saldo de {{token}} insuficiente",
        "Confirmation": "Confirmar",
        "tipAddLiquidity": "Os valores cobrados dos tokens BANA e USDC são uma estimativa. Mas, o valor do token LP recebido é preciso se a transação for executada com êxito. ",
        "WaitingSignature": "Aguardando assinatura",
        "AddConfirmation": "Adicionando {{BANAamount}} BANA e {{USDCamount}} USDC, confirme esta transação na sua carteira.",
        "RemoveConfirmation": "Removendo {{LPamount}} tokens LP, confirme esta transação na sua carteira.",
        "TransactionSubmitted": "Transação enviada",
        "ViewOnEtherscan": "Ver no Etherscan",
        "AddLPToken": "Adicionar token LP",
        "titleAddLiquidity": "Adicionar liquidez",
        "descrAddLiquidity": "Adicione liquidez à reserva de liquidez de BANA-USDC.",
        "descrApprove": "Permita que o contrato acesse seu {{tokenName}}.",
        "RemoveAmount": "Remover quantia",
        "LPToken": "Token LP",
        "confirmation": "Confirmar",
        "tipRemoveLiquidity": "O valor do token LP cobrado é preciso, já os valores dos tokens BANA e USDC recebidos são uma estimativa se a transação for executada com êxito.",
        "": "A quantia total de BANA gasto será atualizada após cada época. As atualizações não serão exibidas durante a execução de uma rodada do evento “Faça trading e ganhe”."
    },
    "bybit_wallet": "nan",
    "createBybitWallet": "Criar Carteira",
    "createBybitWalletTips": "Conecte sua Carteira Bybit Web3 e entre nos gateways para tradings derivativos do Web3.",
    "searchToken": "Pesquisar Tokens",
    "desc_fast_withdraw_fee_by": "nan",
    "assets_by": "Ativos",
    "price_by": "Preço",
    "amount_by": "Quantia",
    "value_by": "Valor",
    "account_by": "Conta",
    "RECEIVED": "",
    "withdraw_confirm_by": "Você sacou {{value}} da sua carteira ApeX Pro. Os fundos estarão refletidos na sua conta em aproximadamente 5 minutos.",
    "ongoing_transaction_by": "Você tem um saque em progresso. Faça uma nova solicitação de saque somente depois que o saque atual for processado.",
    "deposit_dialog_title_by": "Depositar da conta Bybit para",
    "withdraw_dialog_title_by": "Sacar da conta Bybit para",
    "bybit_spot": "nan",
    "AssetAction": {
        "Bybit-Deposit": "nan",
        "Bybit-Withdraw": "nan"
    },
    "withdraw_to": "Sacar para",
    "withdrawal_succ_by": "Saque bem sucedido, veja seus ativos na sua conta Bybit.",
    "BYBIT_WITHDRAW_NOT_ENABLE": "Os saques não estão disponíveis.",
    "INVALID_LP_ACCOUNT_ID": "LP de conta ID inválido. O LP da conta ID é {{lpAccountId}}.",
    "INVALID_LP_L2_KEY": "LP inválido de Chave L2.",
    "BYBIT_WITHDRAW_FINANCE_CIRCUITBREAKER_OPEN": "O circuit breaker da conta financeira agora está aberto. Aguarde o término do processamento antes de fazer um novo saque.",
    "BYBIT_WITHDRAW_ASSETS_DENIED": "Os ativos da conta da contraparte não podem ser sacados.",
    "fast_withdrawal_fee_by": "nan",
    "byWallet": "Carteira Web3",
    "BYBIT_WITHDRAW_NOT_TERMINAL": "Aguarde até que o último saque seja processado com sucesso. A ID do último saque é {{withdrawId}}.",
    "BYBIT_DEPOSIT_SUCCESS": "Sucesso",
    "adjustLeverage": "Ajustar alavancagem",
    "current_lv": "Atual",
    "currentMaxValue_lv": "Alavancagem máxima",
    "positionsMargin_lv": "Margem da posição",
    "adjustTips_lv": "O ajuste de sua alavancagem afetará a alavancagem de sua posição atual e a ordem do maker.",
    "adjustTipsAddWithMargin_lv": "Após os ajustes, a margem da posição aumentou em {{margin}}.",
    "adjustTipsReleaseWithMargin_lv": "Após os ajustes, a margem da posição diminuiu em {{margin}}.",
    "adjustFailedTips_lv": "Alavancagem e margem de conta insuficientes. Ajuste sua alavancagem novamente.",
    "adjustSuccessTips_lv": "Configurações salvas",
    "roleTaker": "Taker",
    "cancelAllActivesTips": "Confirme que você está cancelando todos os pedidos ativos de {{symbol}}.",
    "cancelAllConditionalsTips": "Confirme que você está cancelando todos os pedidos condicionais de {{symbol}}.",
    "resetGridLayout_Setting": "Definido como configuração padrão",
    "redUp_Setting": "Aumentar (vermelho), diminuir (verde)",
    "filledRole": "Papel",
    "roleMaker": "Maker",
    "title_Setting": "Configurações personalizadas",
    "style_Setting": "Estilo",
    "newVersion_Setting": "Nova versão",
    "classical_Setting": "Versão clássica",
    "color_Setting": "Preferências de cor",
    "greenUp_Setting": "Aumentar (verde), diminuir (vermelho)",
    "otherItems_Setting": "Outros",
    "leverage_trade": "alavancagem",
    "push": {
        "task": "Confira",
        "task2": "2. Depositar no aplicativo",
        "task3": "3. Fazer trading no aplicativo",
        "task1": "1. Fazer o download do aplicativo ApeX Pro"
    },
    "detail": {
        "taskslogan": "Complete tarefas fáceis e ganhe até 30 USDC!",
        "tasktitle": "Evento Download do Aplicativo Novo"
    },
    "ORDER_CLIENT_ORDER_ALREADY_EXIST": "A ordem do cliente já existe. A ID da ordem do cliente é {{clientOrderId}}.",
    "ORDER_IS_LIQUIDATE_CANNOT_OPEN_POSITION": "A ordem está sendo liquidada. Não é possível abrir uma nova posição.",
    "ORDER_ASSIGN_IMMEDIATELY_FILL_ACCOUNT_ID_FAILED": "Falha no preenchimento da ID da conta com o envio imediato desta ordem. Lista de contas: {{assignImmediatelyFillAccountIdList}}.",
    "WITHDRAW_INVALID_STATUS": "O status de saque de Ethereum é inválido. O status é {{status}}.",
    "TRANSFER_WITH_SAME_ACCOUNT": "Parâmetro inválido. Transferir para a mesma conta. A ID da conta é {{accountId}}.",
    "TRANSFER_IN_STATUS_INVALID": "Status de transferência de entrada inválido. O status é {{status}}.",
    "TRANSFER_OUT_CENSOR_ROUND_CONFLICT": "Conflito na rodada do censurador de transferência de saída. A rodada de censurador é {{censorRound}}.",
    "CLIENT_TRANSFER_OUT_DATA_CONFLICT": "Conflito de dados do cliente. A ID de transferência do cliente é {{clientTransferId}}.",
    "INVALID_PAGE_NUM": "Página inválida. A página é {{page}}.",
    "CONNECT_WITHDRAW_NOT_TERMINAL": "Novo saque solicitado enquanto o saque existente está em andamento. Acesse o sistema do afiliado.",
    "INVALID_SHORT_URL": "URL curta inválida. Verifique com o provedor do link.",
    "PATH_NOT_BE_FOUND": "Não encontrado: O caminho da solicitação não foi encontrado.",
    "INTERNAL_SERVER_ERROR": "Erro interno do servidor.",
    "TOO_MANY_REQUEST": "Muitas solicitações. Diminua a velocidade e tente novamente mais tarde.",
    "INVALID_L1_TX": "TXID L1 inválido.",
    "INVALID_CUSTOM_INITIAL_MARGIN_RATE": "Taxa de margem inicial personalizada inválida. A taxa de margem inicial é {{customInitialMarginRate}}",
    "ORDER_COULD_NOT_CANCEL_MATCHED": "A ordem foi correspondida. Não é possível cancelar. A ID da ordem é {{orderId}}.",
    "ORDER_COULD_NOT_CANCEL_FILLED": "A ordem foi executada. Não é possível cancelar. A ID da ordem é {{orderId}}.",
    "ORDER_COULD_NOT_CANCEL_INVALID_STATUS": "O status da ordem é inválido. Não é possível cancelar. A ID da ordem é {{orderId}}.",
    "ORDER_LIQUIDATE_FEE_INVALID": "A taxa de liquidação deve ser maior que ou igual a 0. A taxa de liquidação é {{liquidateFee}}.",
    "ORDER_IS_DELEVERAGE_CANNOT_OPEN_POSITION": "A ordem está em desalavancagem. Não é possível abrir uma nova posição.",
    "FAST_WITHDRAW_WALLET_BALANCE_NOT_ENOUGH": "Saque rápido desativado, saldo da carteira insuficiente.",
    "WITHDRAW_CENSOR_ROUND_CONFLICT": "Conflito na rodada do censurador de saque de Ethereum. A rodada de censurador é {{censorRound}}.",
    "WITHDRAW_RISK_CHECK_FAILED": "A verificação de risco de saque de Ethereum falhou.",
    "TRANSFER_PERMISSION_DENIED": "Permissão de transferência negada. A ID da conta é {{accountId}}, a ID da conta do recebedor é {{receiverAccountId}}.",
    "TRANSFER_CONDITION_FACT_REG_ADDRESS_EMPTY": "O fato do endereço registrado não pode estar vazio.",
    "TRANSFER_CONDITION_FACT_EMPTY": "O fato da condição não pode estar vazio.",
    "NOT_CONDITION_TRANSFER_IN": "Transferência de entrada não condicional. A ID da transferência de entrada é {{transferInId}}.",
    "NOT_CONDITION_TRANSFER_OUT": "Transferência de saída não condicional. A ID da transferência de saída é {{transferOutId}}.",
    "TRANSFER_OUT_STATUS_INVALID": "Status de transferência de saída inválido. O status é {{status}}.",
    "TRANSFER_IN_CENSOR_ROUND_CONFLICT": "Conflito na rodada do censurador de transferência de entrada. A rodada de censurador é {{censorRound}}.",
    "TRANSFER_WALLET_BALANCE_NOT_ENOUGH": "Os fundos não puderam ser transferidos. O saldo da carteira era insuficiente.",
    "CONNECT_EMPTY_CLIENT_REFERRAL_WITHDRAW_ID": "A ID de saque de indicação de cliente está vazia.",
    "CONNECT_INVALID_DECIMAL_SCALE_PARAM": "Nome ‘{{name}}’ e valor ‘{{value}}’ inválidos.",
    "CONNECT_INVALID_RANGE_TIME": "Intervalo de tempo inválido. Hora de início: {{beginTime}}, horário de encerramento: {{endTime}}.",
    "CONNECT_WITHDRAW_PAST_DUE": "Tempo de vencimento inválido: {{expireTime}}.",
    "CONNECT_WITHDRAW_NOT_ENABLE": "Os saques não estão disponíveis.",
    "CONNECT_INVALID_IDENTITY": "A autenticação falhou. Acesse o sistema do afiliado.",
    "CONNECT_WITHDRAW_INVALID_AMOUNT": "A verificação do valor do saque falhou.",
    "INVALID_REFERRAL_CODE": "Link ou código de indicação inválido.",
    "CANNOT_BIND_REFERRAL_CODE": "Falha ao emparelhar com este código de indicação.",
    "REQUEST_IS_INVALID": "Erro no serviço de gateway. Sua solicitação é inválida.",
    "IP_IS_BANNED": "IP banido: Seu IP está banido. Altere o endereço IP do dispositivo de login.",
    "SERVER_UNAVAILABLE": "Serviço indisponível: Estamos temporariamente offline para manutenção. Tente novamente mais tarde.",
    "ERROE_REQUEST_PARAM": "Ocorreu uma falha: Erro no parâmetro da solicitação.",
    "API_KEY_AUTH_FAILED": "Requer login: Sua chave API está errada.",
    "REQUEST_TIMEOUT": "O tempo limite da solicitação expirou.",
    "REQUEST_FAILED": "A solicitação falhou.",
    "API_SIGN_ERROR": "Erro de assinatura da API.",
    "PARAM_ILLEGAL": "Parâmetro inválido.",
    "ORDER_WITH_MARKET_PRICE_CANNOT_REDUCE_POSITION_ONLY": "Você não pode reduzir o tamanho da posição para uma ordem com Preço de mercado.",
    "export_DS": "Exportar",
    "exportTitle_DS": "Exportar histórico de ordens",
    "7d_export": "Últimos 7 dias",
    "30_export": "Últimos 30 dias",
    "custom_export": "Personalizar",
    "exportTips_DS": "Você pode exportar um máximo de 10.000 ordens. Por favor, ajuste os parâmetros de tempo caso esteja acima do limite máximo.",
    "generateTxt_DS": "Exportar",
    "marketSeriesTips": "Devido a restrições de prova de conhecimento zero, o spread de compra e venda, além de outros fatores, a sua ordem a mercado poderá ser cancelada. Se a sua ordem a mercado for cancelada, você poderá enviar outra ordem a mercado ou optar por enviar uma ordem limitada.",
    "TIME_LIMIT_HAS_NOT_EXPIRED": "Você pode baixar este arquivo novamente em 10 minutos.",
    "generatingTxt_DS": "Exportando",
    "tradeVolume": "Volume de trading",
    "tradePerson": "Nº de traders",
    "rateTrades": "Taxa de ganho por trades",
    "rateDays": "Taxa de ganho por dias",
    "winnerTrades": "Ganho (em trades)",
    "lostTrades": "Perda (em trades)",
    "lostDays": "Perda (em dias)",
    "personalInfo": "Perfil",
    "ratePair": "Maior taxa de ganho por mercado",
    "winnerDays": "Ganho (em dias)",
    "kLineSetting": "Configurações do gráfico",
    "NaN": "Exibição de informações",
    "showCurrentActiveOrders": "Exibit detalhes da ordem",
    "position_kline": "Posições",
    "limitOrder_kline": "Ordem limitada",
    "showCurrentPositions": "Mostrar informação das posições",
    "dayVolume": "Volume de trading em 24h",
    "totalVolume": "Volume de trading acumulado",
    "winRateEmptyTips": "Nenhum trading recente registrado. Obtenha as recompensas máximas enquanto faz trading — aproveite ganhos múltiplos agora.",
    "countRate": "Taxa",
    "tradeCount": "Trades totais",
    "dayCount": "Dias",
    "mvpTrader": {
        "TradePopUpTitle": "LIGA DE TRADERS MVP",
        "TradePopUpDesc": "Prêmio de até 100.000 USDC",
        "TradePopUpButton": "Inscrições abertas"
    },
    "installBybitWallet": "Download Bybit Wallet",
    "openPositionTpOSlTips": "Please place a reverse order; your TP/SL order will be invalid otherwise. ",
    "ORDER_OPEN_TAKE_PROFIT_STOP_LOSS_SETTING_AT_LEAST_ONE": "For TP/SL, please set a minimum of either one TP or SL order.",
    "ORDER_OPEN_TAKE_PROFIT_STOP_LOSS_ORDER_NUM_EXCEEDS_MAX_VALUE": "To open a new position and execute TP/SL, maximum order size per contract is {{maxSize}}.",
    "reason_USER_CANCELED": "User has initiated cancellation of the order.",
    "reason_EXPIRED": "This order has expired and will be automatically canceled.",
    "reason_REDUCE_ONLY_CANCELED": "Order does not fulfil the conditions of a Reduce-Only order and will be automatically canceled.",
    "reason_LIQUIDATE_CANCELED": "Due to forced liquidation, the order will be automatically canceled.",
    "reason_POSITION_TPSL_EVICTED": "TP/SL has been triggered on this order; the order will be automatically canceled.",
    "reason_SYSTEM_LIMIT_EVICTED": "The order does not fulfil margin requirements and will be automatically canceled.",
    "reason_UNKNOWN_ORDER_CANCEL_REASON": "Errors were detected with your order. To ensure the safety of your assets, this order has been automatically canceled.",
    "orderCancelTips": "({{side}}) of {{qty}} {{token}} has been canceled.",
    "reason_COULD_NOT_FILL": "This order has triggered Post-Only, FOK, IOC or GTT conditions and will be automatically canceled.",
    "reason_INTERNAL_FAILED": "Errors were detected with your order. To ensure the safety of your assets, this order has been automatically canceled.",
    "reason_ADMIN_CANCELED": "Due to errors in your order, the order has been automatically canceled to ensure the safety of your assets."
}
